simple_time/__init__.py
simple_time/__main__.py
simple_time/server.py
simple_time_mcp_server-0.1.1.dist-info/licenses/LICENSE
simple_time_mcp_server-0.1.1.dist-info/METADATA
simple_time_mcp_server-0.1.1.dist-info/WHEEL
simple_time_mcp_server-0.1.1.dist-info/entry_points.txt
simple_time_mcp_server-0.1.1.dist-info/top_level.txt
simple_time_mcp_server-0.1.1.dist-info/RECORD
