Metadata-Version: 2.4
Name: simple-time-mcp-server
Version: 0.1.1
Summary: Add your description here
Requires-Python: >=3.13
License-File: LICENSE
Requires-Dist: mcp>=1.5.0
Requires-Dist: ntplib>=0.4.0
Dynamic: license-file
